LICENSE
README.rst
setup.py
FrEIA/__init__.py
FrEIA.egg-info/PKG-INFO
FrEIA.egg-info/SOURCES.txt
FrEIA.egg-info/dependency_links.txt
FrEIA.egg-info/requires.txt
FrEIA.egg-info/top_level.txt
FrEIA/framework/__init__.py
FrEIA/framework/graph_inn.py
FrEIA/framework/reversible_graph_net.py
FrEIA/framework/reversible_sequential_net.py
FrEIA/framework/sequence_inn.py
FrEIA/modules/__init__.py
FrEIA/modules/all_in_one_block.py
FrEIA/modules/base.py
FrEIA/modules/coupling_layers.py
FrEIA/modules/fixed_transforms.py
FrEIA/modules/gaussian_mixture.py
FrEIA/modules/graph_topology.py
FrEIA/modules/inv_auto_layers.py
FrEIA/modules/invertible_resnet.py
FrEIA/modules/orthogonal.py
FrEIA/modules/reshapes.py