Metadata-Version: 2.1
Name: FrEIA
Version: 0.2
Summary: Framework for Easily Invertible Architectures
Home-page: https://github.com/VLL-HD/FrEIA
Author: VLL-HD team and collaborators
Author-email: 
License: UNKNOWN
Project-URL: Bug Reports, https://github.com/VLL-HD/FrEIA/issues
Project-URL: Source, https://github.com/VLL-HD/FrEIA
Platform: UNKNOWN
Classifier: Programming Language :: Python :: 3
Classifier: License :: OSI Approved :: MIT License
Classifier: Operating System :: OS Independent
Requires-Python: >=3.6
License-File: LICENSE
